braandket_synthesis/__init__.py
braandket_synthesis/basics/__init__.py
braandket_synthesis/basics/operation_and_trait.py
braandket_synthesis/operations/__init__.py
braandket_synthesis/operations/gates/__init__.py
braandket_synthesis/operations/gates/gates.py
braandket_synthesis/operations/measurement/__init__.py
braandket_synthesis/operations/measurement/desired.py
braandket_synthesis/operations/measurement/projective.py
braandket_synthesis/operations/measurement/result.py
braandket_synthesis/operations/numeric/__init__.py
braandket_synthesis/operations/numeric/matrix.py
braandket_synthesis/operations/numeric/qubits_matrix.py
braandket_synthesis/operations/structural/__init__.py
braandket_synthesis/operations/structural/controlled.py
braandket_synthesis/operations/structural/remapped.py
braandket_synthesis/operations/structural/sequential.py
braandket_synthesis/traits/__init__.py
braandket_synthesis/traits/apply.py
braandket_synthesis/traits/diagonal.py
braandket_synthesis/traits/hermitian.py
braandket_synthesis/traits/measure.py
braandket_synthesis/traits/tensor.py
braandket_synthesis/traits/unitary.py
braandket_synthesis/utils/__init__.py
braandket_synthesis/utils/iter_structured.py
braandket_synthesis-0.2.2.dist-info/LICENSE.txt
braandket_synthesis-0.2.2.dist-info/METADATA
braandket_synthesis-0.2.2.dist-info/WHEEL
braandket_synthesis-0.2.2.dist-info/top_level.txt
braandket_synthesis-0.2.2.dist-info/RECORD
