Metadata-Version: 2.1
Name: braandket-synthesis
Version: 0.2.2
Summary: A library for quantum circuit synthesis based on BraAndKet.
Classifier: Programming Language :: Python :: 3
Classifier: License :: OSI Approved :: MIT License
Classifier: Operating System :: OS Independent
Requires-Python: >=3.7
License-File: LICENSE.txt
Requires-Dist: braandket (>=0.8.1)
